py_analytics_api/__init__.py
py_analytics_api/py_analytics_api.py
test/__init__.py
test/test_qa.py
py_analytics-0.0.4.dist-info/LICENSE
py_analytics-0.0.4.dist-info/METADATA
py_analytics-0.0.4.dist-info/WHEEL
py_analytics-0.0.4.dist-info/top_level.txt
py_analytics-0.0.4.dist-info/RECORD
